LICENSE
MANIFEST.in
README.rst
setup.cfg
setup.py
versioneer.py
CBVadmin.egg-info/PKG-INFO
CBVadmin.egg-info/SOURCES.txt
CBVadmin.egg-info/dependency_links.txt
CBVadmin.egg-info/not-zip-safe
CBVadmin.egg-info/requires.txt
CBVadmin.egg-info/top_level.txt
cbvadmin/__init__.py
cbvadmin/_version.py
cbvadmin/actions.py
cbvadmin/apps.py
cbvadmin/cbvadmin.py
cbvadmin/checks.py
cbvadmin/decorators.py
cbvadmin/fields.py
cbvadmin/forms.py
cbvadmin/layout.py
cbvadmin/menus.py
cbvadmin/options.py
cbvadmin/permissions.py
cbvadmin/sites.py
cbvadmin/tables.py
cbvadmin/utils.py
cbvadmin.egg-info/PKG-INFO
cbvadmin.egg-info/SOURCES.txt
cbvadmin.egg-info/dependency_links.txt
cbvadmin.egg-info/not-zip-safe
cbvadmin.egg-info/requires.txt
cbvadmin.egg-info/top_level.txt
cbvadmin/templates/cbvadmin/registration/password_reset_email.html
cbvadmin/views/__init__.py
cbvadmin/views/auth.py
cbvadmin/views/dashboard.py
cbvadmin/views/detail.py
cbvadmin/views/edit.py
cbvadmin/views/list.py
cbvadmin/views/mixins.py
cbvadmin/views/user.py